gc_overrides/__init__.py
gc_overrides/dal/__init__.py
gc_overrides/dal/connect_db.py
gc_overrides/featureextraction/__init__.py
gc_overrides/featureextraction/featureextraction.py
gc_overrides-0.1.0.dist-info/entry_points.txt
gc_overrides-0.1.0.dist-info/WHEEL
gc_overrides-0.1.0.dist-info/METADATA
gc_overrides-0.1.0.dist-info/RECORD
