Metadata-Version: 2.1
Name: gc-overrides
Version: 0.1.0
Summary: 
Author: Tova Hallas
Author-email: tova.hallas@igentify.com
Requires-Python: >=3.8,<4.0
Classifier: Programming Language :: Python :: 3
Classifier: Programming Language :: Python :: 3.8
Classifier: Programming Language :: Python :: 3.9
Requires-Dist: pandas (>=1.2.4,<2.0.0)
Requires-Dist: psycopg2 (>=2.8.6,<3.0.0)
Requires-Dist: sklearn (>=0.0,<0.1)
